{
  "items": [
    {
      "name": "Michael De Santa",
      "img": "placeholder"
    },
    {
      "name": "Trevor Philips",
      "img": "placeholder"
    },
    {
      "name": "Franklin Clinton",
      "img": "placeholder"
    },
    {
      "name": "Amanda De Santa",
      "img": "placeholder"
    },
    {
      "name": "Jimmy De Santa",
      "img": "placeholder"
    },
    {
      "name": "Tracey De Santa",
      "img": "placeholder"
    },
    {
      "name": "Lamar Davis",
      "img": "placeholder"
    },
    {
      "name": "Ron Jakowski",
      "img": "placeholder"
    },
    {
      "name": "Wade Hebert",
      "img": "placeholder"
    },
    {
      "name": "Denise Clinton",
      "img": "placeholder"
    },
    {
      "name": "Tanisha Jackson",
      "img": "placeholder"
    },
    {
      "name": "Steve Haines",
      "img": "placeholder"
    },
    {
      "name": "Devin Weston",
      "img": "placeholder"
    },
    {
      "name": "Stretch",
      "img": "placeholder"
    },
    {
      "name": "Wei Cheng",
      "img": "placeholder"
    },
    {
      "name": "Lester Crest",
      "img": "placeholder"
    },
    {
      "name": "Dave Norton",
      "img": "placeholder"
    },
    {
      "name": "Brad Snider",
      "img": "placeholder"
    },
    {
      "name": "Martin Madrazo",
      "img": "placeholder"
    },
    {
      "name": "Liz Macallen",
      "img": "placeholder"
    },
    {
      "name": "Solomon Richards",
      "img": "placeholder"
    },
    {
      "name": "Molly Schultz",
      "img": "placeholder"
    },
    {
      "name": "Mary-Ann Quinn",
      "img": "placeholder"
    },
    {
      "name": "Tonya Wiggins",
      "img": "placeholder"
    },
    {
      "name": "Simeon Yetarian",
      "img": "placeholder"
    },
    {
      "name": "Beverly Felton",
      "img": "placeholder"
    },
    {
      "name": "Fabien LaRouche",
      "img": "placeholder"
    },
    {
      "name": "Hao",
      "img": "placeholder"
    },
    {
      "name": "Rocco Pelosi",
      "img": "placeholder"
    },
    {
      "name": "Lazlow Jones",
      "img": "placeholder"
    }
  ]
}
