{
  "items": [
    {
      "name": "The Legend of Zelda (1986)",
      "img": "placeholder"
    },
    {
      "name": "Zelda II: The Adventure of Link (1987)",
      "img": "placeholder"
    },
    {
      "name": "The Legend of Zelda: A Link to the Past (1991)",
      "img": "placeholder"
    },
    {
      "name": "The Legend of Zelda: Link's Awakening (1993)",
      "img": "placeholder"
    },
    {
      "name": "The Legend of Zelda: Ocarina of Time (1998)",
      "img": "placeholder"
    },
    {
      "name": "The Legend of Zelda: Majora's Mask (2000)",
      "img": "placeholder"
    },
    {
      "name": "The Legend of Zelda: Oracle of Ages (2001)",
      "img": "placeholder"
    },
    {
      "name": "The Legend of Zelda: Oracle of Seasons (2001)",
      "img": "placeholder"
    },
    {
      "name": "The Legend of Zelda: A Link to the Past & Four Swords (2002)",
      "img": "placeholder"
    },
    {
      "name": "The Legend of Zelda: The Wind Waker (2002)",
      "img": "placeholder"
    },
    {
      "name": "The Legend of Zelda: Four Swords Adventures (2004)",
      "img": "placeholder"
    },
    {
      "name": "The Legend of Zelda: The Minish Cap (2004)",
      "img": "placeholder"
    },
    {
      "name": "The Legend of Zelda: Twilight Princess (2006)",
      "img": "placeholder"
    },
    {
      "name": "The Legend of Zelda: Phantom Hourglass (2007)",
      "img": "placeholder"
    },
    {
      "name": "The Legend of Zelda: Spirit Tracks (2009)",
      "img": "placeholder"
    },
    {
      "name": "The Legend of Zelda: Skyward Sword (2011)",
      "img": "placeholder"
    },
    {
      "name": "The Legend of Zelda: A Link Between Worlds (2013)",
      "img": "placeholder"
    },
    {
      "name": "The Legend of Zelda: Tri Force Heroes (2015)",
      "img": "placeholder"
    },
    {
      "name": "The Legend of Zelda: Breath of the Wild (2017)",
      "img": "placeholder"
    },
    {
      "name": "The Legend of Zelda: Link's Awakening (2019)",
      "img": "placeholder"
    },
    {
      "name": "The Legend of Zelda: Skyward Sword (2021)",
      "img": "placeholder"
    },
    {
      "name": "The Legend of Zelda: Tears of the Kingdom (2023)",
      "img": "placeholder"
    }
  ]
}
